evaluationary/__init__.py
evalutionary-0.1.0.dist-info/METADATA
evalutionary-0.1.0.dist-info/WHEEL
evalutionary-0.1.0.dist-info/top_level.txt
evalutionary-0.1.0.dist-info/RECORD
