Metadata-Version: 2.2
Name: evalutionary
Version: 0.1.0
Summary: Evolve your AI application with evals!
Author-email: Nick Byrne <nbyrne@quansight.com>
License: MIT
Classifier: Programming Language :: Python :: 3
Classifier: License :: OSI Approved :: MIT License
Classifier: Operating System :: OS Independent
Requires-Python: >=3.9
